davipy/__init__.py
davipy/downloadimgs.py
davipy/isevenodd.py
davipy/isprime.py
davipy/listlink.py
davipy/ping.py
davipy/removelistduplicate.py
davipy/reportfile.py
davipy/singledownload.py
davipy/stringalowerupper.py
davipy-0.0.1.dist-info/METADATA
davipy-0.0.1.dist-info/WHEEL
davipy-0.0.1.dist-info/top_level.txt
davipy-0.0.1.dist-info/RECORD
