Metadata-Version: 2.1
Name: davipy
Version: 0.0.1
Summary: Python library for shortcuts
Author: Davide Soltys
Author-email: <Davide02072003@gmail.com>
Requires-Dist: pandas
Requires-Dist: beautifulsoup4
